aesb/__init__.py
aesb/config.py
aesb/data_fetcher.py
aesb/data_processor.py
aesb/database.py
aesb/main.py
aesb/tools.py
aesb/visualizer.py
aesb-2.0.0.dist-info/LICENSE
aesb-2.0.0.dist-info/METADATA
aesb-2.0.0.dist-info/WHEEL
aesb-2.0.0.dist-info/top_level.txt
aesb-2.0.0.dist-info/RECORD
