Metadata-Version: 2.1
Name: aesb
Version: 2.0.0
Summary: A Python package for battery cell data analysis and visualization.
License: Copyright (c) 2023, [Your Name]
Project-URL: Homepage, https://github.com/pypa/sampleproject
Project-URL: Bug Tracker, https://github.com/pypa/sampleproject/issues
Classifier: Programming Language :: Python :: 3
Classifier: License :: OSI Approved :: MIT License
Classifier: Operating System :: OS Independent
Requires-Python: >=3.8
License-File: LICENSE
Requires-Dist: pandas
Requires-Dist: numpy
Requires-Dist: matplotlib
Requires-Dist: scikit-learn
Requires-Dist: requests
Requires-Dist: sqlalchemy
Requires-Dist: pymysql
Requires-Dist: tqdm
